{"date":"2026-07-02","metrics":{"totalStars":68,"avgScore":231.8,"dominantLanguage":"Python","dominantColor":"#3572A5","languageDistribution":{"Python":6,"HTML":1,"TypeScript":1,"JavaScript":1,"Rust":1}},"topRepos":[{"name":"KittenML/KittenTTS","language":"Python","color":"#3572A5","stars":12,"score":254.3987},{"name":"xbtlin/ai-berkshire","language":"Python","color":"#3572A5","stars":11,"score":253.9291},{"name":"Panniantong/Agent-Reach","language":"Python","color":"#3572A5","stars":9,"score":240.9485},{"name":"XxHuberrr/Mineradio","language":"HTML","color":"#e34c26","stars":8,"score":237.3429},{"name":"usestrix/strix","language":"Python","color":"#3572A5","stars":6,"score":226.9367},{"name":"facebook/astryx","language":"TypeScript","color":"#3178c6","stars":5,"score":226.3795},{"name":"browser-use/video-use","language":"Python","color":"#3572A5","stars":5,"score":222.9846},{"name":"Yu9191/wloc","language":"JavaScript","color":"#f1e05a","stars":4,"score":218.8942},{"name":"hugohe3/ppt-master","language":"Python","color":"#3572A5","stars":4,"score":218.167},{"name":"ogulcancelik/herdr","language":"Rust","color":"#dea584","stars":4,"score":218.0227}]}