{"date":"2026-05-11","metrics":{"totalStars":1672,"avgScore":900.57,"dominantLanguage":"Python","dominantColor":"#3572A5","languageDistribution":{"Python":3,"Shell":1,"Zig":1,"TypeScript":2,"JavaScript":1,"Go":1,"Rust":1}},"topRepos":[{"name":"anthropics/financial-services-plugins","language":"Python","color":"#3572A5","stars":300,"score":1445.5517},{"name":"addyosmani/agent-skills","language":"Shell","color":"#89e051","stars":198,"score":990.266},{"name":"vercel-labs/zero-native","language":"Zig","color":"#8b8b8b","stars":198,"score":954.6439},{"name":"ruvnet/ruflo","language":"TypeScript","color":"#3178c6","stars":156,"score":876.5073},{"name":"rohitg00/agentmemory","language":"TypeScript","color":"#3178c6","stars":150,"score":848.6768},{"name":"decolua/9router","language":"JavaScript","color":"#f1e05a","stars":155,"score":836.017},{"name":"datawhalechina/hello-agents","language":"Python","color":"#3572A5","stars":157,"score":819.3649},{"name":"masterking32/MasterDnsVPN","language":"Go","color":"#00ADD8","stars":142,"score":794.1289},{"name":"jackwener/wx-cli","language":"Rust","color":"#dea584","stars":106,"score":770.0521},{"name":"Yuan1z0825/nature-skills","language":"Python","color":"#3572A5","stars":110,"score":670.4545}]}