{"date":"2026-06-28","metrics":{"totalStars":414,"avgScore":386.4,"dominantLanguage":"Python","dominantColor":"#3572A5","languageDistribution":{"Python":4,"C":1,"TypeScript":3,"Go":1,"Unknown":1}},"topRepos":[{"name":"calesthio/OpenMontage","language":"Python","color":"#3572A5","stars":85,"score":587.8524},{"name":"DeusData/codebase-memory-mcp","language":"C","color":"#555555","stars":76,"score":546.3166},{"name":"Panniantong/Agent-Reach","language":"Python","color":"#3572A5","stars":55,"score":443.1033},{"name":"JCodesMore/ai-website-cloner-template","language":"TypeScript","color":"#3178c6","stars":38,"score":363.7948},{"name":"xbtlin/ai-berkshire","language":"Python","color":"#3572A5","stars":33,"score":358.0357},{"name":"Lakr233/AssppWeb","language":"TypeScript","color":"#3178c6","stars":28,"score":323.656},{"name":"mauriceboe/TREK","language":"TypeScript","color":"#3178c6","stars":28,"score":321.4436},{"name":"hugohe3/ppt-master","language":"Python","color":"#3572A5","stars":25,"score":311.8674},{"name":"kunchenguid/no-mistakes","language":"Go","color":"#00ADD8","stars":24,"score":305.0026},{"name":"Leonxlnx/taste-skill","language":"Unknown","color":"#8b8b8b","stars":22,"score":302.9326}]}